{
  "FD001": {
    "dataset": "FD001",
    "seed": 42,
    "n_train": 1702,
    "n_test": 2250,
    "probe_best_val": 0.3910297751426697,
    "pooled_auprc": 0.9256835471173395,
    "pooled_auroc": 0.9298696607983479,
    "per_horizon": [
      {
        "dt": 1,
        "auroc": 0.7734568303164474,
        "auprc": 0.42159545458806014,
        "pos_rate": 0.024888888888888887,
        "pred_gap": 0.12810158729553223
      },
      {
        "dt": 5,
        "auroc": 0.7552736123282711,
        "auprc": 0.42488474551720484,
        "pos_rate": 0.11955555555555555,
        "pred_gap": 0.0659477561712265
      },
      {
        "dt": 10,
        "auroc": 0.7354614315299726,
        "auprc": 0.49712260144458054,
        "pos_rate": 0.22444444444444445,
        "pred_gap": 0.06524808704853058
      },
      {
        "dt": 20,
        "auroc": 0.6655180840664712,
        "auprc": 0.5891928259121717,
        "pos_rate": 0.41333333333333333,
        "pred_gap": 0.08891671895980835
      },
      {
        "dt": 50,
        "auroc": 0.6098211134434269,
        "auprc": 0.8357274774858372,
        "pos_rate": 0.7631111111111111,
        "pred_gap": 0.023490309715270996
      },
      {
        "dt": 100,
        "auroc": 0.4627324136544069,
        "auprc": 0.9506304490168828,
        "pos_rate": 0.9568888888888889,
        "pred_gap": -0.0047879815101623535
      },
      {
        "dt": 150,
        "auroc": 0.3684299191374663,
        "auprc": 0.9838459835652367,
        "pos_rate": 0.9893333333333333,
        "pred_gap": -0.010969400405883789
      }
    ],
    "surface_path": "/home/sagemaker-user/IndustrialJEPA/fam-jepa/experiments/v27/surfaces/chronos2_FD001_s42.npz"
  },
  "FD002": {
    "dataset": "FD002",
    "seed": 42,
    "n_train": 4428,
    "n_test": 6979,
    "probe_best_val": 0.38087594509124756,
    "pooled_auprc": 0.9145613965774841,
    "pooled_auroc": 0.9272308197760919,
    "per_horizon": [
      {
        "dt": 1,
        "auroc": 0.9023200287823119,
        "auprc": 0.3436340077393884,
        "pos_rate": 0.01920045851841238,
        "pred_gap": 0.047405995428562164
      },
      {
        "dt": 5,
        "auroc": 0.8583543989582092,
        "auprc": 0.4077504750676535,
        "pos_rate": 0.09342312652242442,
        "pred_gap": 0.12750054895877838
      },
      {
        "dt": 10,
        "auroc": 0.7760302695001312,
        "auprc": 0.4594571663485752,
        "pos_rate": 0.18283421693652385,
        "pred_gap": 0.1851920783519745
      },
      {
        "dt": 20,
        "auroc": 0.7021918770175448,
        "auprc": 0.544631451956711,
        "pos_rate": 0.3460381143430291,
        "pred_gap": 0.16383004188537598
      },
      {
        "dt": 50,
        "auroc": 0.6067129616558152,
        "auprc": 0.7595357029295651,
        "pos_rate": 0.678463963318527,
        "pred_gap": 0.03502953052520752
      },
      {
        "dt": 100,
        "auroc": 0.5982458429971685,
        "auprc": 0.9381630407415414,
        "pos_rate": 0.909156039547213,
        "pred_gap": 0.008862674236297607
      },
      {
        "dt": 150,
        "auroc": 0.6037758437214958,
        "auprc": 0.9895290199301738,
        "pos_rate": 0.9835219945550938,
        "pred_gap": 0.002471625804901123
      }
    ],
    "surface_path": "/home/sagemaker-user/IndustrialJEPA/fam-jepa/experiments/v27/surfaces/chronos2_FD002_s42.npz"
  },
  "FD003": {
    "dataset": "FD003",
    "seed": 42,
    "n_train": 2651,
    "n_test": 5222,
    "probe_best_val": 0.5264672040939331,
    "pooled_auprc": 0.7974525073360188,
    "pooled_auroc": 0.8953613521435286,
    "per_horizon": [
      {
        "dt": 1,
        "auroc": 0.9103771148133798,
        "auprc": 0.3653846900954253,
        "pos_rate": 0.011489850631941785,
        "pred_gap": 0.1519782692193985
      },
      {
        "dt": 5,
        "auroc": 0.8484972343425179,
        "auprc": 0.27303088339585707,
        "pos_rate": 0.05572577556491766,
        "pred_gap": 0.11243073642253876
      },
      {
        "dt": 10,
        "auroc": 0.7999135228215015,
        "auprc": 0.3333058331502985,
        "pos_rate": 0.10877058598238223,
        "pred_gap": 0.16251561045646667
      },
      {
        "dt": 20,
        "auroc": 0.7206974230288787,
        "auprc": 0.38290710268788763,
        "pos_rate": 0.20968977403293756,
        "pred_gap": 0.15877312421798706
      },
      {
        "dt": 50,
        "auroc": 0.6429165502493559,
        "auprc": 0.6086529182158298,
        "pos_rate": 0.4574875526618154,
        "pred_gap": 0.06334471702575684
      },
      {
        "dt": 100,
        "auroc": 0.6173356201798331,
        "auprc": 0.815484550175683,
        "pos_rate": 0.7142857142857143,
        "pred_gap": 0.011225283145904541
      },
      {
        "dt": 150,
        "auroc": 0.5981492422341197,
        "auprc": 0.9030795213047659,
        "pos_rate": 0.8517809268479509,
        "pred_gap": -0.0001895427703857422
      }
    ],
    "surface_path": "/home/sagemaker-user/IndustrialJEPA/fam-jepa/experiments/v27/surfaces/chronos2_FD003_s42.npz"
  },
  "SMAP": {
    "dataset": "SMAP",
    "seed": 42,
    "n_train": 64846,
    "n_test": 120639,
    "probe_best_val": 11.495670318603516,
    "pooled_auprc": 0.2918781920526989,
    "pooled_auroc": 0.5088147104496293,
    "per_horizon": [
      {
        "dt": 1,
        "auroc": 0.5113309835743363,
        "auprc": 0.305374615063809,
        "pos_rate": 0.27905569509031075,
        "pred_gap": 0.001557469367980957
      },
      {
        "dt": 5,
        "auroc": 0.504077344664251,
        "auprc": 0.300525807777406,
        "pos_rate": 0.27922147895788263,
        "pred_gap": 0.001825571060180664
      },
      {
        "dt": 10,
        "auroc": 0.5121607095216386,
        "auprc": 0.309183307989054,
        "pos_rate": 0.27942870879234744,
        "pred_gap": 0.001879572868347168
      },
      {
        "dt": 20,
        "auroc": 0.5113710700844543,
        "auprc": 0.3061293077329752,
        "pos_rate": 0.27984316846127705,
        "pred_gap": 0.0016203224658966064
      },
      {
        "dt": 50,
        "auroc": 0.511649092464707,
        "auprc": 0.3199784738973378,
        "pos_rate": 0.2810865474680659,
        "pred_gap": 0.0012115240097045898
      },
      {
        "dt": 100,
        "auroc": 0.49303582247350436,
        "auprc": 0.318155651235715,
        "pos_rate": 0.28315884581271394,
        "pred_gap": 0.0009286403656005859
      },
      {
        "dt": 150,
        "auroc": 0.47386231375157706,
        "auprc": 0.29806590625710716,
        "pos_rate": 0.28523114415736206,
        "pred_gap": 0.0008638501167297363
      },
      {
        "dt": 200,
        "auroc": 0.502026126773466,
        "auprc": 0.33372862258846286,
        "pos_rate": 0.28707963428078814,
        "pred_gap": 0.002119779586791992
      }
    ],
    "surface_path": "/home/sagemaker-user/IndustrialJEPA/fam-jepa/experiments/v27/surfaces/chronos2_SMAP_s42.npz"
  },
  "MSL": {
    "dataset": "MSL",
    "seed": 42,
    "n_train": 9627,
    "n_test": 15302,
    "probe_best_val": 1.3078274726867676,
    "pooled_auprc": 0.22321570603971816,
    "pooled_auroc": 0.5354805292356046,
    "per_horizon": [
      {
        "dt": 1,
        "auroc": 0.5040632784615575,
        "auprc": 0.17095320707115555,
        "pos_rate": 0.17808129656254085,
        "pred_gap": -0.0003879070281982422
      },
      {
        "dt": 5,
        "auroc": 0.5011988600853299,
        "auprc": 0.1724555369334616,
        "pos_rate": 0.17964971899098156,
        "pred_gap": -0.000797569751739502
      },
      {
        "dt": 10,
        "auroc": 0.49540481354537946,
        "auprc": 0.1710848054140819,
        "pos_rate": 0.18161024702653247,
        "pred_gap": -0.0009554028511047363
      },
      {
        "dt": 20,
        "auroc": 0.4815330659484727,
        "auprc": 0.17201192007847266,
        "pos_rate": 0.1855313030976343,
        "pred_gap": -0.0017917156219482422
      },
      {
        "dt": 50,
        "auroc": 0.5136361673902404,
        "auprc": 0.19532315887619334,
        "pos_rate": 0.19729447131093975,
        "pred_gap": 0.00043851137161254883
      },
      {
        "dt": 100,
        "auroc": 0.547263026800596,
        "auprc": 0.22532782874831633,
        "pos_rate": 0.2133708012024572,
        "pred_gap": 0.0033646821975708008
      },
      {
        "dt": 150,
        "auroc": 0.541033371717396,
        "auprc": 0.23416362866049403,
        "pos_rate": 0.22317344138021172,
        "pred_gap": 0.0023061633110046387
      },
      {
        "dt": 200,
        "auroc": 0.5989672289060921,
        "auprc": 0.270639458485647,
        "pos_rate": 0.23219187034374592,
        "pred_gap": 0.004169821739196777
      }
    ],
    "surface_path": "/home/sagemaker-user/IndustrialJEPA/fam-jepa/experiments/v27/surfaces/chronos2_MSL_s42.npz"
  },
  "PSM": {
    "dataset": "PSM",
    "seed": 42,
    "n_train": 13144,
    "n_test": 26024,
    "probe_best_val": 1.1771118640899658,
    "pooled_auprc": 0.422343226886179,
    "pooled_auroc": 0.5467243970162304,
    "per_horizon": [
      {
        "dt": 1,
        "auroc": 0.5171944596957623,
        "auprc": 0.38407756876051014,
        "pos_rate": 0.3289655702428528,
        "pred_gap": 0.0050442516803741455
      },
      {
        "dt": 5,
        "auroc": 0.5214503529184752,
        "auprc": 0.39969103393682404,
        "pos_rate": 0.33203965570242855,
        "pred_gap": 0.006839185953140259
      },
      {
        "dt": 10,
        "auroc": 0.521237489197595,
        "auprc": 0.40358539689885004,
        "pos_rate": 0.3357669843221642,
        "pred_gap": 0.00670391321182251
      },
      {
        "dt": 20,
        "auroc": 0.5263321630685787,
        "auprc": 0.41200136953273936,
        "pos_rate": 0.34272210267445435,
        "pred_gap": 0.007025539875030518
      },
      {
        "dt": 50,
        "auroc": 0.5274439123097733,
        "auprc": 0.43419137311814504,
        "pos_rate": 0.36028281586228095,
        "pred_gap": 0.0070269107818603516
      },
      {
        "dt": 100,
        "auroc": 0.5113732709984555,
        "auprc": 0.4401972355984731,
        "pos_rate": 0.38572087304027053,
        "pred_gap": 0.0032786130905151367
      },
      {
        "dt": 150,
        "auroc": 0.5049085093997867,
        "auprc": 0.4493226983288086,
        "pos_rate": 0.40877651398708886,
        "pred_gap": 0.0019903182983398438
      },
      {
        "dt": 200,
        "auroc": 0.48709729411960406,
        "auprc": 0.4587446120041114,
        "pos_rate": 0.43183215493390714,
        "pred_gap": -0.001083672046661377
      }
    ],
    "surface_path": "/home/sagemaker-user/IndustrialJEPA/fam-jepa/experiments/v27/surfaces/chronos2_PSM_s42.npz"
  },
  "MBA": {
    "dataset": "MBA",
    "seed": 42,
    "n_train": 1120,
    "n_test": 1975,
    "probe_best_val": 0.49847957491874695,
    "pooled_auprc": 0.9194788112157792,
    "pooled_auroc": 0.8342419857584549,
    "per_horizon": [
      {
        "dt": 1,
        "auroc": 0.5774760203460999,
        "auprc": 0.46684726833021667,
        "pos_rate": 0.35037974683544304,
        "pred_gap": 0.007764488458633423
      },
      {
        "dt": 5,
        "auroc": 0.6095159967186218,
        "auprc": 0.5406176097047848,
        "pos_rate": 0.3827848101265823,
        "pred_gap": 0.012240290641784668
      },
      {
        "dt": 10,
        "auroc": 0.6098603870599157,
        "auprc": 0.5947475828709287,
        "pos_rate": 0.4232911392405063,
        "pred_gap": 0.01286768913269043
      },
      {
        "dt": 20,
        "auroc": 0.6259542767597458,
        "auprc": 0.6320360009195443,
        "pos_rate": 0.5043037974683544,
        "pred_gap": 0.016324520111083984
      },
      {
        "dt": 50,
        "auroc": 0.45653230580401993,
        "auprc": 0.7217316243446521,
        "pos_rate": 0.7473417721518988,
        "pred_gap": -0.004386305809020996
      },
      {
        "dt": 100,
        "auroc": 0.6968270571827055,
        "auprc": 0.9873355897363866,
        "pos_rate": 0.9681012658227848,
        "pred_gap": 0.01784992218017578
      },
      {
        "dt": 150,
        "auroc": 0.6494350936047968,
        "auprc": 0.988124670712216,
        "pos_rate": 0.9726582278481013,
        "pred_gap": 0.011504769325256348
      },
      {
        "dt": 200,
        "auroc": 0.7506410627181059,
        "auprc": 0.9920975242403048,
        "pos_rate": 0.9726582278481013,
        "pred_gap": 0.024639666080474854
      }
    ],
    "surface_path": "/home/sagemaker-user/IndustrialJEPA/fam-jepa/experiments/v27/surfaces/chronos2_MBA_s42.npz"
  },
  "GECCO": {
    "dataset": "GECCO",
    "seed": 42,
    "n_train": 17414,
    "n_test": 34563,
    "probe_best_val": 1.3224050998687744,
    "pooled_auprc": 0.03131640982148025,
    "pooled_auroc": 0.8717778433343967,
    "per_horizon": [
      {
        "dt": 1,
        "auroc": 0.981151771733457,
        "auprc": 0.0871042070548247,
        "pos_rate": 0.0022278158724647746,
        "pred_gap": 0.5224817991256714
      },
      {
        "dt": 5,
        "auroc": 0.9616400326239276,
        "auprc": 0.08331533129261721,
        "pos_rate": 0.0023435465671382692,
        "pred_gap": 0.49763771891593933
      },
      {
        "dt": 10,
        "auroc": 0.94953359536624,
        "auprc": 0.07892819422307676,
        "pos_rate": 0.0024882099354801377,
        "pred_gap": 0.45507073402404785
      },
      {
        "dt": 20,
        "auroc": 0.9154985807680777,
        "auprc": 0.07122645165405034,
        "pos_rate": 0.0027775366721638746,
        "pred_gap": 0.3950166702270508
      },
      {
        "dt": 50,
        "auroc": 0.8383814289816554,
        "auprc": 0.056359257456426476,
        "pos_rate": 0.0036455168822150854,
        "pred_gap": 0.27194729447364807
      },
      {
        "dt": 100,
        "auroc": 0.7543760756575556,
        "auprc": 0.04305353324765164,
        "pos_rate": 0.00509215056563377,
        "pred_gap": 0.16392594575881958
      },
      {
        "dt": 150,
        "auroc": 0.6765048848207035,
        "auprc": 0.03538718536574818,
        "pos_rate": 0.006538784249052455,
        "pred_gap": 0.10002774000167847
      },
      {
        "dt": 200,
        "auroc": 0.641281839612174,
        "auprc": 0.03159061044676378,
        "pos_rate": 0.00798541793247114,
        "pred_gap": 0.06619936227798462
      }
    ],
    "surface_path": "/home/sagemaker-user/IndustrialJEPA/fam-jepa/experiments/v27/surfaces/chronos2_GECCO_s42.npz"
  },
  "BATADAL": {
    "dataset": "BATADAL",
    "seed": 42,
    "n_train": 595,
    "n_test": 1077,
    "probe_best_val": 2.888808250427246,
    "pooled_auprc": 0.3358364760842042,
    "pooled_auroc": 0.7019569592512815,
    "per_horizon": [
      {
        "dt": 1,
        "auroc": 0.5051278836509528,
        "auprc": 0.06839777566823242,
        "pos_rate": 0.07428040854224698,
        "pred_gap": 0.020161181688308716
      },
      {
        "dt": 5,
        "auroc": 0.33658884088611085,
        "auprc": 0.057712974725331406,
        "pos_rate": 0.08170844939647168,
        "pred_gap": -0.004896223545074463
      },
      {
        "dt": 10,
        "auroc": 0.6175710324988013,
        "auprc": 0.11132576455882459,
        "pos_rate": 0.09099350046425256,
        "pred_gap": 0.0035539567470550537
      },
      {
        "dt": 20,
        "auroc": 0.5300984429402096,
        "auprc": 0.1049932927405946,
        "pos_rate": 0.1095636025998143,
        "pred_gap": 0.000775068998336792
      },
      {
        "dt": 50,
        "auroc": 0.49655359888015405,
        "auprc": 0.1528451104773505,
        "pos_rate": 0.16527390900649955,
        "pred_gap": -0.0010991096496582031
      },
      {
        "dt": 100,
        "auroc": 0.3416906024617103,
        "auprc": 0.1879805689120542,
        "pos_rate": 0.25812441968430827,
        "pred_gap": -0.003945112228393555
      },
      {
        "dt": 150,
        "auroc": 0.6441306931292625,
        "auprc": 0.4558270299766575,
        "pos_rate": 0.35097493036211697,
        "pred_gap": 0.00366818904876709
      },
      {
        "dt": 200,
        "auroc": 0.3554529515720063,
        "auprc": 0.37778720339124267,
        "pos_rate": 0.4438254410399257,
        "pred_gap": -0.0056667327880859375
      }
    ],
    "surface_path": "/home/sagemaker-user/IndustrialJEPA/fam-jepa/experiments/v27/surfaces/chronos2_BATADAL_s42.npz"
  }
}