{
  "results": {
    "FD001": {
      "probe_h@1.0": {
        "n_seeds": 3,
        "per_seed": [
          {
            "subset": "FD001",
            "mode": "probe_h",
            "budget": 1.0,
            "seed": 42,
            "primary": {
              "auprc": 0.9088414667176702,
              "auroc": 0.9812306443368712,
              "f1_best": 0.8369230769230769,
              "precision_best": 0.8143712574850299,
              "recall_best": 0.8607594936708861,
              "threshold_best": 0.8276031613349915,
              "prevalence": 0.158,
              "n_cells": 1000,
              "n_positive": 158
            },
            "per_horizon": {
              "auprc_per_k": [
                NaN,
                NaN,
                NaN,
                NaN,
                0.6881880024737167,
                0.8557034632034631,
                0.884174430641822,
                0.9226827447512452,
                0.9582059234541818,
                0.9385708464123154
              ],
              "auroc_per_k": [
                NaN,
                NaN,
                NaN,
                NaN,
                0.9815668202764978,
                0.9844444444444445,
                0.96875,
                0.9728,
                0.9715061058344641,
                0.8860244233378561
              ],
              "horizon_labels": [
                1,
                2,
                3,
                5,
                10,
                15,
                20,
                30,
                50,
                100
              ],
              "prevalence_per_k": [
                0.0,
                0.0,
                0.0,
                0.0,
                0.07,
                0.1,
                0.16,
                0.25,
                0.33,
                0.67
              ]
            },
            "monotonicity": {
              "violation_rate": 0.0,
              "mean_violation": 0.0,
              "max_violation": 0.0,
              "n_pairs": 900
            },
            "legacy": {
              "rmse_cross": 19.158288955688477,
              "rmse_expected": 22.53205108642578,
              "rmse_uncapped": 30.99394989013672,
              "nasa_score": 803.4645385742188,
              "horizon_cap": 100.0
            },
            "train": {
              "best_val": 0.38169579950968424,
              "final_epoch": 21
            },
            "pos_weight": 7.284600389863548,
            "n_train_items": 425,
            "surface_file": "/home/sagemaker-user/IndustrialJEPA/fam-jepa/experiments/v21/surfaces/fd001_probe_h_b100_seed42.npz",
            "runtime_s": 4.666544198989868
          },
          {
            "subset": "FD001",
            "mode": "probe_h",
            "budget": 1.0,
            "seed": 123,
            "primary": {
              "auprc": 0.9228901668094255,
              "auroc": 0.9854325145073515,
              "f1_best": 0.857142857142857,
              "precision_best": 0.8414634146341463,
              "recall_best": 0.8734177215189873,
              "threshold_best": 0.7916267514228821,
              "prevalence": 0.158,
              "n_cells": 1000,
              "n_positive": 158
            },
            "per_horizon": {
              "auprc_per_k": [
                NaN,
                NaN,
                NaN,
                NaN,
                0.763095238095238,
                0.8046142746142746,
                0.8662991890673526,
                0.9602186450452975,
                0.9636467474064461,
                0.9542470693803982
              ],
              "auroc_per_k": [
                NaN,
                NaN,
                NaN,
                NaN,
                0.9769585253456221,
                0.9822222222222222,
                0.9761904761904763,
                0.9861333333333333,
                0.9782903663500679,
                0.905924920850294
              ],
              "horizon_labels": [
                1,
                2,
                3,
                5,
                10,
                15,
                20,
                30,
                50,
                100
              ],
              "prevalence_per_k": [
                0.0,
                0.0,
                0.0,
                0.0,
                0.07,
                0.1,
                0.16,
                0.25,
                0.33,
                0.67
              ]
            },
            "monotonicity": {
              "violation_rate": 0.0,
              "mean_violation": 0.0,
              "max_violation": 0.0,
              "n_pairs": 900
            },
            "legacy": {
              "rmse_cross": 15.920112609863281,
              "rmse_expected": 19.38580894470215,
              "rmse_uncapped": 28.35262680053711,
              "nasa_score": 516.046875,
              "horizon_cap": 100.0
            },
            "train": {
              "best_val": 0.42402578830718995,
              "final_epoch": 17
            },
            "pos_weight": 8.340659340659341,
            "n_train_items": 425,
            "surface_file": "/home/sagemaker-user/IndustrialJEPA/fam-jepa/experiments/v21/surfaces/fd001_probe_h_b100_seed123.npz",
            "runtime_s": 2.5035626888275146
          },
          {
            "subset": "FD001",
            "mode": "probe_h",
            "budget": 1.0,
            "seed": 456,
            "primary": {
              "auprc": 0.9533422176389574,
              "auroc": 0.9883076761177425,
              "f1_best": 0.8910256410256411,
              "precision_best": 0.9025974025974026,
              "recall_best": 0.879746835443038,
              "threshold_best": 0.8489588499069214,
              "prevalence": 0.158,
              "n_cells": 1000,
              "n_positive": 158
            },
            "per_horizon": {
              "auprc_per_k": [
                NaN,
                NaN,
                NaN,
                NaN,
                0.799145299145299,
                0.9999999999999999,
                0.98359375,
                0.9556834451072842,
                0.9881468265632488,
                0.9655641834376268
              ],
              "auroc_per_k": [
                NaN,
                NaN,
                NaN,
                NaN,
                0.9754224270353303,
                1.0,
                0.9962797619047619,
                0.984,
                0.9936680235187697,
                0.9240162822252375
              ],
              "horizon_labels": [
                1,
                2,
                3,
                5,
                10,
                15,
                20,
                30,
                50,
                100
              ],
              "prevalence_per_k": [
                0.0,
                0.0,
                0.0,
                0.0,
                0.07,
                0.1,
                0.16,
                0.25,
                0.33,
                0.67
              ]
            },
            "monotonicity": {
              "violation_rate": 0.0,
              "mean_violation": 0.0,
              "max_violation": 0.0,
              "n_pairs": 900
            },
            "legacy": {
              "rmse_cross": 13.270267486572266,
              "rmse_expected": 14.930685997009277,
              "rmse_uncapped": 23.571596145629883,
              "nasa_score": 284.3982849121094,
              "horizon_cap": 100.0
            },
            "train": {
              "best_val": 0.3518419278462728,
              "final_epoch": 25
            },
            "pos_weight": 7.1106870229007635,
            "n_train_items": 425,
            "surface_file": "/home/sagemaker-user/IndustrialJEPA/fam-jepa/experiments/v21/surfaces/fd001_probe_h_b100_seed456.npz",
            "runtime_s": 3.5583438873291016
          }
        ],
        "auprc_mean": 0.9283579503886843,
        "auprc_std": 0.022748663721014948,
        "auprc_ci95_lo": 0.8718471369480848,
        "auprc_ci95_hi": 0.9848687638292838,
        "auroc_mean": 0.9849902783206551,
        "auroc_std": 0.0035591816953456194,
        "auroc_ci95_lo": 0.9761487808483852,
        "auroc_ci95_hi": 0.993831775792925,
        "f1_best_mean": 0.8616971916971917,
        "f1_best_std": 0.02733730661646502,
        "f1_best_ci95_lo": 0.7937875573943907,
        "f1_best_ci95_hi": 0.9296068259999928,
        "precision_best_mean": 0.852810691572193,
        "precision_best_std": 0.0451943988872394,
        "precision_best_ci95_lo": 0.7405415809379058,
        "precision_best_ci95_hi": 0.9650798022064803,
        "recall_best_mean": 0.871308016877637,
        "recall_best_std": 0.009667881212986996,
        "recall_best_ci95_lo": 0.8472916685640312,
        "recall_best_ci95_hi": 0.8953243651912429,
        "rmse_expected_mean": 18.949515342712402,
        "rmse_expected_std": 3.8194177417510753,
        "rmse_expected_ci95_lo": 9.46155569361785,
        "rmse_expected_ci95_hi": 28.437474991806955,
        "rmse_cross_mean": 16.116223017374676,
        "rmse_cross_std": 2.948905504444669,
        "rmse_cross_ci95_lo": 8.790735645486322,
        "rmse_cross_ci95_hi": 23.44171038926303,
        "nasa_mean": 534.6365661621094,
        "nasa_std": 260.03197185313826,
        "nasa_ci95_lo": -111.31866137106681,
        "nasa_ci95_hi": 1180.5917936952856,
        "mono_violation_mean": 0.0,
        "mono_violation_std": 0.0,
        "mono_violation_ci95_lo": 0.0,
        "mono_violation_ci95_hi": 0.0
      },
      "probe_h@0.05": {
        "n_seeds": 3,
        "per_seed": [
          {
            "subset": "FD001",
            "mode": "probe_h",
            "budget": 0.05,
            "seed": 42,
            "primary": {
              "auprc": 0.8484457717658046,
              "auroc": 0.9703275805045251,
              "f1_best": 0.7964601769911503,
              "precision_best": 0.7458563535911602,
              "recall_best": 0.8544303797468354,
              "threshold_best": 0.7089582085609436,
              "prevalence": 0.158,
              "n_cells": 1000,
              "n_positive": 158
            },
            "per_horizon": {
              "auprc_per_k": [
                NaN,
                NaN,
                NaN,
                NaN,
                0.7253968253968254,
                0.8901574732457084,
                0.8790707148243913,
                0.9018781396553688,
                0.9537697536872338,
                0.9127700039702198
              ],
              "auroc_per_k": [
                NaN,
                NaN,
                NaN,
                NaN,
                0.9861751152073733,
                0.9844444444444445,
                0.96875,
                0.9674666666666666,
                0.9696969696969697,
                0.8367254635911352
              ],
              "horizon_labels": [
                1,
                2,
                3,
                5,
                10,
                15,
                20,
                30,
                50,
                100
              ],
              "prevalence_per_k": [
                0.0,
                0.0,
                0.0,
                0.0,
                0.07,
                0.1,
                0.16,
                0.25,
                0.33,
                0.67
              ]
            },
            "monotonicity": {
              "violation_rate": 0.0,
              "mean_violation": 0.0,
              "max_violation": 0.0,
              "n_pairs": 900
            },
            "legacy": {
              "rmse_cross": 24.157814025878906,
              "rmse_expected": 26.384767532348633,
              "rmse_uncapped": 34.83861541748047,
              "nasa_score": 1279.3087158203125,
              "horizon_cap": 100.0
            },
            "train": {
              "best_val": 0.44590515581766765,
              "final_epoch": 28
            },
            "pos_weight": 6.142857142857143,
            "n_train_items": 20,
            "surface_file": "/home/sagemaker-user/IndustrialJEPA/fam-jepa/experiments/v21/surfaces/fd001_probe_h_b5_seed42.npz",
            "runtime_s": 1.3750076293945312
          },
          {
            "subset": "FD001",
            "mode": "probe_h",
            "budget": 0.05,
            "seed": 123,
            "primary": {
              "auprc": 0.8592538254608215,
              "auroc": 0.9622771279954297,
              "f1_best": 0.7500000000000001,
              "precision_best": 0.8947368421052632,
              "recall_best": 0.6455696202531646,
              "threshold_best": 0.8489843606948853,
              "prevalence": 0.158,
              "n_cells": 1000,
              "n_positive": 158
            },
            "per_horizon": {
              "auprc_per_k": [
                NaN,
                NaN,
                NaN,
                NaN,
                0.4176147382029735,
                0.49384031817855345,
                0.5660848898854415,
                0.9532472165291201,
                0.9552682518480435,
                0.9339266815504422
              ],
              "auroc_per_k": [
                NaN,
                NaN,
                NaN,
                NaN,
                0.9416282642089093,
                0.9444444444444445,
                0.9241071428571428,
                0.9845333333333334,
                0.9715061058344641,
                0.8570782451379467
              ],
              "horizon_labels": [
                1,
                2,
                3,
                5,
                10,
                15,
                20,
                30,
                50,
                100
              ],
              "prevalence_per_k": [
                0.0,
                0.0,
                0.0,
                0.0,
                0.07,
                0.1,
                0.16,
                0.25,
                0.33,
                0.67
              ]
            },
            "monotonicity": {
              "violation_rate": 0.0,
              "mean_violation": 0.0,
              "max_violation": 0.0,
              "n_pairs": 900
            },
            "legacy": {
              "rmse_cross": 19.014467239379883,
              "rmse_expected": 21.734127044677734,
              "rmse_uncapped": 31.26304054260254,
              "nasa_score": 677.9219970703125,
              "horizon_cap": 100.0
            },
            "train": {
              "best_val": 1.06026988474528,
              "final_epoch": 27
            },
            "pos_weight": 11.5,
            "n_train_items": 20,
            "surface_file": "/home/sagemaker-user/IndustrialJEPA/fam-jepa/experiments/v21/surfaces/fd001_probe_h_b5_seed123.npz",
            "runtime_s": 1.3259079456329346
          },
          {
            "subset": "FD001",
            "mode": "probe_h",
            "budget": 0.05,
            "seed": 456,
            "primary": {
              "auprc": 0.8895602079688746,
              "auroc": 0.9734921374665504,
              "f1_best": 0.8184615384615385,
              "precision_best": 0.7964071856287425,
              "recall_best": 0.8417721518987342,
              "threshold_best": 0.7517067193984985,
              "prevalence": 0.158,
              "n_cells": 1000,
              "n_positive": 158
            },
            "per_horizon": {
              "auprc_per_k": [
                NaN,
                NaN,
                NaN,
                NaN,
                0.7337257980115122,
                0.7712809412809413,
                0.9643421052631579,
                0.9228201749305869,
                0.9611318439390816,
                0.9507249896175558
              ],
              "auroc_per_k": [
                NaN,
                NaN,
                NaN,
                NaN,
                0.978494623655914,
                0.9811111111111112,
                0.9903273809523809,
                0.9648000000000001,
                0.981456354590683,
                0.8968792401628223
              ],
              "horizon_labels": [
                1,
                2,
                3,
                5,
                10,
                15,
                20,
                30,
                50,
                100
              ],
              "prevalence_per_k": [
                0.0,
                0.0,
                0.0,
                0.0,
                0.07,
                0.1,
                0.16,
                0.25,
                0.33,
                0.67
              ]
            },
            "monotonicity": {
              "violation_rate": 0.0,
              "mean_violation": 0.0,
              "max_violation": 0.0,
              "n_pairs": 900
            },
            "legacy": {
              "rmse_cross": 21.837352752685547,
              "rmse_expected": 21.8985652923584,
              "rmse_uncapped": 31.394973754882812,
              "nasa_score": 924.3106689453125,
              "horizon_cap": 100.0
            },
            "train": {
              "best_val": 0.5843576774597168,
              "final_epoch": 30
            },
            "pos_weight": 6.142857142857143,
            "n_train_items": 20,
            "surface_file": "/home/sagemaker-user/IndustrialJEPA/fam-jepa/experiments/v21/surfaces/fd001_probe_h_b5_seed456.npz",
            "runtime_s": 1.437304973602295
          }
        ],
        "auprc_mean": 0.8657532683985002,
        "auprc_std": 0.021313875408972068,
        "auprc_ci95_lo": 0.8128066667121808,
        "auprc_ci95_hi": 0.9186998700848196,
        "auroc_mean": 0.9686989486555017,
        "auroc_std": 0.0057821657390696845,
        "auroc_ci95_lo": 0.954335252687666,
        "auroc_ci95_hi": 0.9830626446233374,
        "f1_best_mean": 0.7883072384842297,
        "f1_best_std": 0.03495137145883401,
        "f1_best_ci95_lo": 0.7014832185670219,
        "f1_best_ci95_hi": 0.8751312584014375,
        "precision_best_mean": 0.8123334604417219,
        "precision_best_std": 0.07570722975458416,
        "precision_best_ci95_lo": 0.6242662759585433,
        "precision_best_ci95_hi": 1.0004006449249006,
        "recall_best_mean": 0.7805907172995781,
        "recall_best_std": 0.11710286148842125,
        "recall_best_ci95_lo": 0.4896910829259204,
        "recall_best_ci95_hi": 1.0714903516732357,
        "rmse_expected_mean": 23.339153289794922,
        "rmse_expected_std": 2.638860468111109,
        "rmse_expected_ci95_lo": 16.78386048499422,
        "rmse_expected_ci95_hi": 29.894446094595622,
        "rmse_cross_mean": 21.669878005981445,
        "rmse_cross_std": 2.575760059600886,
        "rmse_cross_ci95_lo": 15.2713353055859,
        "rmse_cross_ci95_hi": 28.06842070637699,
        "nasa_mean": 960.5137939453125,
        "nasa_std": 302.3234957244427,
        "nasa_ci95_lo": 209.50059707734158,
        "nasa_ci95_hi": 1711.5269908132834,
        "mono_violation_mean": 0.0,
        "mono_violation_std": 0.0,
        "mono_violation_ci95_lo": 0.0,
        "mono_violation_ci95_hi": 0.0
      },
      "pred_ft@1.0": {
        "n_seeds": 3,
        "per_seed": [
          {
            "subset": "FD001",
            "mode": "pred_ft",
            "budget": 1.0,
            "seed": 42,
            "primary": {
              "auprc": 0.9272191947263946,
              "auroc": 0.983027150545717,
              "f1_best": 0.8528528528528528,
              "precision_best": 0.8114285714285714,
              "recall_best": 0.8987341772151899,
              "threshold_best": 0.8425960540771484,
              "prevalence": 0.158,
              "n_cells": 1000,
              "n_positive": 158
            },
            "per_horizon": {
              "auprc_per_k": [
                NaN,
                NaN,
                NaN,
                NaN,
                0.8429499072356215,
                0.8752888777888778,
                0.8892727177713591,
                0.9403164476006987,
                0.965467646388699,
                0.9481000482286064
              ],
              "auroc_per_k": [
                NaN,
                NaN,
                NaN,
                NaN,
                0.9861751152073733,
                0.9877777777777778,
                0.9709821428571429,
                0.9792,
                0.9791949344188151,
                0.8896426956128448
              ],
              "horizon_labels": [
                1,
                2,
                3,
                5,
                10,
                15,
                20,
                30,
                50,
                100
              ],
              "prevalence_per_k": [
                0.0,
                0.0,
                0.0,
                0.0,
                0.07,
                0.1,
                0.16,
                0.25,
                0.33,
                0.67
              ]
            },
            "monotonicity": {
              "violation_rate": 0.0,
              "mean_violation": 0.0,
              "max_violation": 0.0,
              "n_pairs": 900
            },
            "legacy": {
              "rmse_cross": 17.788198471069336,
              "rmse_expected": 21.580324172973633,
              "rmse_uncapped": 30.954299926757812,
              "nasa_score": 558.3443603515625,
              "horizon_cap": 100.0
            },
            "train": {
              "best_val": 0.34782946395874026,
              "final_epoch": 14
            },
            "pos_weight": 7.284600389863548,
            "n_train_items": 425,
            "surface_file": "/home/sagemaker-user/IndustrialJEPA/fam-jepa/experiments/v21/surfaces/fd001_pred_ft_b100_seed42.npz",
            "runtime_s": 2.299234390258789
          },
          {
            "subset": "FD001",
            "mode": "pred_ft",
            "budget": 1.0,
            "seed": 123,
            "primary": {
              "auprc": 0.947672481639147,
              "auroc": 0.9888451246279203,
              "f1_best": 0.8807339449541285,
              "precision_best": 0.8520710059171598,
              "recall_best": 0.9113924050632911,
              "threshold_best": 0.9209077954292297,
              "prevalence": 0.158,
              "n_cells": 1000,
              "n_positive": 158
            },
            "per_horizon": {
              "auprc_per_k": [
                NaN,
                NaN,
                NaN,
                NaN,
                0.857142857142857,
                0.871976911976912,
                0.8681519558657717,
                0.9745273486747172,
                0.984517376562831,
                0.9601034018231059
              ],
              "auroc_per_k": [
                NaN,
                NaN,
                NaN,
                NaN,
                0.9877112135176651,
                0.9877777777777778,
                0.9769345238095238,
                0.9914666666666667,
                0.9914066033469019,
                0.9154228855721392
              ],
              "horizon_labels": [
                1,
                2,
                3,
                5,
                10,
                15,
                20,
                30,
                50,
                100
              ],
              "prevalence_per_k": [
                0.0,
                0.0,
                0.0,
                0.0,
                0.07,
                0.1,
                0.16,
                0.25,
                0.33,
                0.67
              ]
            },
            "monotonicity": {
              "violation_rate": 0.0,
              "mean_violation": 0.0,
              "max_violation": 0.0,
              "n_pairs": 900
            },
            "legacy": {
              "rmse_cross": 11.570652961730957,
              "rmse_expected": 17.288803100585938,
              "rmse_uncapped": 26.715940475463867,
              "nasa_score": 320.3043212890625,
              "horizon_cap": 100.0
            },
            "train": {
              "best_val": 0.2756799996693929,
              "final_epoch": 17
            },
            "pos_weight": 8.340659340659341,
            "n_train_items": 425,
            "surface_file": "/home/sagemaker-user/IndustrialJEPA/fam-jepa/experiments/v21/surfaces/fd001_pred_ft_b100_seed123.npz",
            "runtime_s": 2.744417667388916
          },
          {
            "subset": "FD001",
            "mode": "pred_ft",
            "budget": 1.0,
            "seed": 456,
            "primary": {
              "auprc": 0.9591832432655489,
              "auroc": 0.9901680748068191,
              "f1_best": 0.8819444444444443,
              "precision_best": 0.9769230769230769,
              "recall_best": 0.8037974683544303,
              "threshold_best": 0.967666745185852,
              "prevalence": 0.158,
              "n_cells": 1000,
              "n_positive": 158
            },
            "per_horizon": {
              "auprc_per_k": [
                NaN,
                NaN,
                NaN,
                NaN,
                0.9276437847866419,
                0.9651515151515152,
                0.9647490887380594,
                0.9830543203922515,
                0.9883196780729988,
                0.9665242628886451
              ],
              "auroc_per_k": [
                NaN,
                NaN,
                NaN,
                NaN,
                0.9923195084485408,
                0.9955555555555555,
                0.9933035714285714,
                0.9941333333333333,
                0.9936680235187697,
                0.9217548620533695
              ],
              "horizon_labels": [
                1,
                2,
                3,
                5,
                10,
                15,
                20,
                30,
                50,
                100
              ],
              "prevalence_per_k": [
                0.0,
                0.0,
                0.0,
                0.0,
                0.07,
                0.1,
                0.16,
                0.25,
                0.33,
                0.67
              ]
            },
            "monotonicity": {
              "violation_rate": 0.0,
              "mean_violation": 0.0,
              "max_violation": 0.0,
              "n_pairs": 900
            },
            "legacy": {
              "rmse_cross": 11.021797180175781,
              "rmse_expected": 12.31298542022705,
              "rmse_uncapped": 21.450458526611328,
              "nasa_score": 168.1862030029297,
              "horizon_cap": 100.0
            },
            "train": {
              "best_val": 0.29625116793314615,
              "final_epoch": 23
            },
            "pos_weight": 7.1106870229007635,
            "n_train_items": 425,
            "surface_file": "/home/sagemaker-user/IndustrialJEPA/fam-jepa/experiments/v21/surfaces/fd001_pred_ft_b100_seed456.npz",
            "runtime_s": 3.57119083404541
          }
        ],
        "auprc_mean": 0.9446916398770302,
        "auprc_std": 0.016189168075025927,
        "auprc_ci95_lo": 0.9044755169404922,
        "auprc_ci95_hi": 0.9849077628135682,
        "auroc_mean": 0.9873467833268187,
        "auroc_std": 0.003798943249989284,
        "auroc_ci95_lo": 0.9779096851348379,
        "auroc_ci95_hi": 0.9967838815187995,
        "f1_best_mean": 0.8718437474171418,
        "f1_best_std": 0.01645773023590954,
        "f1_best_ci95_lo": 0.8309604790888119,
        "f1_best_ci95_hi": 0.9127270157454717,
        "precision_best_mean": 0.8801408847562694,
        "precision_best_std": 0.08624410942638022,
        "precision_best_ci95_lo": 0.6658986401165311,
        "precision_best_ci95_hi": 1.0943831293960076,
        "recall_best_mean": 0.871308016877637,
        "recall_best_std": 0.058807425589731475,
        "recall_best_ci95_lo": 0.725222273241044,
        "recall_best_ci95_hi": 1.01739376051423,
        "rmse_expected_mean": 17.060704231262207,
        "rmse_expected_std": 4.637878147405311,
        "rmse_expected_ci95_lo": 5.539576222932691,
        "rmse_expected_ci95_hi": 28.581832239591723,
        "rmse_cross_mean": 13.460216204325357,
        "rmse_cross_std": 3.758175560451426,
        "rmse_cross_ci95_lo": 4.12439056734523,
        "rmse_cross_ci95_hi": 22.796041841305485,
        "nasa_mean": 348.94496154785156,
        "nasa_std": 196.6495910045204,
        "nasa_ci95_lo": -139.55970346070228,
        "nasa_ci95_hi": 837.4496265564054,
        "mono_violation_mean": 0.0,
        "mono_violation_std": 0.0,
        "mono_violation_ci95_lo": 0.0,
        "mono_violation_ci95_hi": 0.0
      },
      "pred_ft@0.05": {
        "n_seeds": 3,
        "per_seed": [
          {
            "subset": "FD001",
            "mode": "pred_ft",
            "budget": 0.05,
            "seed": 42,
            "primary": {
              "auprc": 0.8773594494135303,
              "auroc": 0.9720902612826604,
              "f1_best": 0.8307692307692308,
              "precision_best": 0.8083832335329342,
              "recall_best": 0.8544303797468354,
              "threshold_best": 0.9171043038368225,
              "prevalence": 0.158,
              "n_cells": 1000,
              "n_positive": 158
            },
            "per_horizon": {
              "auprc_per_k": [
                NaN,
                NaN,
                NaN,
                NaN,
                0.715532879818594,
                0.7321767040149393,
                0.8630245752599327,
                0.8992914189129781,
                0.9431924637208482,
                0.9394799133880894
              ],
              "auroc_per_k": [
                NaN,
                NaN,
                NaN,
                NaN,
                0.9815668202764977,
                0.9755555555555556,
                0.9635416666666666,
                0.9674666666666667,
                0.9651741293532338,
                0.8756218905472637
              ],
              "horizon_labels": [
                1,
                2,
                3,
                5,
                10,
                15,
                20,
                30,
                50,
                100
              ],
              "prevalence_per_k": [
                0.0,
                0.0,
                0.0,
                0.0,
                0.07,
                0.1,
                0.16,
                0.25,
                0.33,
                0.67
              ]
            },
            "monotonicity": {
              "violation_rate": 0.0,
              "mean_violation": 0.0,
              "max_violation": 0.0,
              "n_pairs": 900
            },
            "legacy": {
              "rmse_cross": 21.740514755249023,
              "rmse_expected": 24.361740112304688,
              "rmse_uncapped": 31.166982650756836,
              "nasa_score": 1198.482421875,
              "horizon_cap": 100.0
            },
            "train": {
              "best_val": 0.5785214920043945,
              "final_epoch": 24
            },
            "pos_weight": 6.142857142857143,
            "n_train_items": 20,
            "surface_file": "/home/sagemaker-user/IndustrialJEPA/fam-jepa/experiments/v21/surfaces/fd001_pred_ft_b5_seed42.npz",
            "runtime_s": 1.2468628883361816
          },
          {
            "subset": "FD001",
            "mode": "pred_ft",
            "budget": 0.05,
            "seed": 123,
            "primary": {
              "auprc": 0.7580701945828411,
              "auroc": 0.9122230073062929,
              "f1_best": 0.6626506024096386,
              "precision_best": 0.632183908045977,
              "recall_best": 0.6962025316455697,
              "threshold_best": 0.9366766214370728,
              "prevalence": 0.158,
              "n_cells": 1000,
              "n_positive": 158
            },
            "per_horizon": {
              "auprc_per_k": [
                NaN,
                NaN,
                NaN,
                NaN,
                0.842517006802721,
                0.891976911976912,
                0.8895301609939769,
                0.9675365672339358,
                0.9684072217672945,
                0.9440817324900237
              ],
              "auroc_per_k": [
                NaN,
                NaN,
                NaN,
                NaN,
                0.9831029185867896,
                0.9888888888888888,
                0.9776785714285714,
                0.9887999999999999,
                0.9810040705563094,
                0.8819538670284939
              ],
              "horizon_labels": [
                1,
                2,
                3,
                5,
                10,
                15,
                20,
                30,
                50,
                100
              ],
              "prevalence_per_k": [
                0.0,
                0.0,
                0.0,
                0.0,
                0.07,
                0.1,
                0.16,
                0.25,
                0.33,
                0.67
              ]
            },
            "monotonicity": {
              "violation_rate": 0.0,
              "mean_violation": 0.0,
              "max_violation": 0.0,
              "n_pairs": 900
            },
            "legacy": {
              "rmse_cross": 31.20480728149414,
              "rmse_expected": 28.16504669189453,
              "rmse_uncapped": 34.859130859375,
              "nasa_score": 2018.534423828125,
              "horizon_cap": 100.0
            },
            "train": {
              "best_val": 0.8940416132609049,
              "final_epoch": 13
            },
            "pos_weight": 11.5,
            "n_train_items": 20,
            "surface_file": "/home/sagemaker-user/IndustrialJEPA/fam-jepa/experiments/v21/surfaces/fd001_pred_ft_b5_seed123.npz",
            "runtime_s": 0.7493162155151367
          },
          {
            "subset": "FD001",
            "mode": "pred_ft",
            "budget": 0.05,
            "seed": 456,
            "primary": {
              "auprc": 0.7898519810203891,
              "auroc": 0.9442594485703116,
              "f1_best": 0.6906474820143884,
              "precision_best": 0.555984555984556,
              "recall_best": 0.9113924050632911,
              "threshold_best": 0.5378293395042419,
              "prevalence": 0.158,
              "n_cells": 1000,
              "n_positive": 158
            },
            "per_horizon": {
              "auprc_per_k": [
                NaN,
                NaN,
                NaN,
                NaN,
                0.323524359238645,
                0.481535594035594,
                0.6797784429370528,
                0.8265174478971953,
                0.9229631043397035,
                0.9547279607645298
              ],
              "auroc_per_k": [
                NaN,
                NaN,
                NaN,
                NaN,
                0.8924731182795699,
                0.9088888888888889,
                0.921875,
                0.9424,
                0.9701492537313432,
                0.903663500678426
              ],
              "horizon_labels": [
                1,
                2,
                3,
                5,
                10,
                15,
                20,
                30,
                50,
                100
              ],
              "prevalence_per_k": [
                0.0,
                0.0,
                0.0,
                0.0,
                0.07,
                0.1,
                0.16,
                0.25,
                0.33,
                0.67
              ]
            },
            "monotonicity": {
              "violation_rate": 0.0,
              "mean_violation": 0.0,
              "max_violation": 0.0,
              "n_pairs": 900
            },
            "legacy": {
              "rmse_cross": 20.94588279724121,
              "rmse_expected": 18.436180114746094,
              "rmse_uncapped": 26.273530960083008,
              "nasa_score": 586.0238037109375,
              "horizon_cap": 100.0
            },
            "train": {
              "best_val": 0.6041080754597982,
              "final_epoch": 14
            },
            "pos_weight": 6.142857142857143,
            "n_train_items": 20,
            "surface_file": "/home/sagemaker-user/IndustrialJEPA/fam-jepa/experiments/v21/surfaces/fd001_pred_ft_b5_seed456.npz",
            "runtime_s": 0.7968378067016602
          }
        ],
        "auprc_mean": 0.8084272083389202,
        "auprc_std": 0.061775892401215886,
        "auprc_ci95_lo": 0.654967384349931,
        "auprc_ci95_hi": 0.9618870323279095,
        "auroc_mean": 0.9428575723864218,
        "auroc_std": 0.02995823705250262,
        "auroc_ci95_lo": 0.8684371859476662,
        "auroc_ci95_hi": 1.0172779588251772,
        "f1_best_mean": 0.7280224383977526,
        "f1_best_std": 0.0900757116201224,
        "f1_best_ci95_lo": 0.5042619662522321,
        "f1_best_ci95_hi": 0.9517829105432731,
        "precision_best_mean": 0.6655172325211557,
        "precision_best_std": 0.12945889694211135,
        "precision_best_ci95_lo": 0.3439235045096427,
        "precision_best_ci95_hi": 0.9871109605326687,
        "recall_best_mean": 0.820675105485232,
        "recall_best_std": 0.11149544524661441,
        "recall_best_ci95_lo": 0.5437050652631554,
        "recall_best_ci95_hi": 1.0976451457073086,
        "rmse_expected_mean": 23.654322306315105,
        "rmse_expected_std": 4.902860510269727,
        "rmse_expected_ci95_lo": 11.47494161745354,
        "rmse_expected_ci95_hi": 35.83370299517667,
        "rmse_cross_mean": 24.630401611328125,
        "rmse_cross_std": 5.707448416245663,
        "rmse_cross_ci95_lo": 10.452313762838278,
        "rmse_cross_ci95_hi": 38.80848945981797,
        "nasa_mean": 1267.6802164713542,
        "nasa_std": 718.7579010138822,
        "nasa_ci95_lo": -517.8133910336148,
        "nasa_ci95_hi": 3053.1738239763235,
        "mono_violation_mean": 0.0,
        "mono_violation_std": 0.0,
        "mono_violation_ci95_lo": 0.0,
        "mono_violation_ci95_hi": 0.0
      },
      "e2e@1.0": {
        "n_seeds": 3,
        "per_seed": [
          {
            "subset": "FD001",
            "mode": "e2e",
            "budget": 1.0,
            "seed": 42,
            "primary": {
              "auprc": 0.9684982114830502,
              "auroc": 0.9937986710364113,
              "f1_best": 0.9085365853658536,
              "precision_best": 0.8764705882352941,
              "recall_best": 0.9430379746835443,
              "threshold_best": 0.9020405411720276,
              "prevalence": 0.158,
              "n_cells": 1000,
              "n_positive": 158
            },
            "per_horizon": {
              "auprc_per_k": [
                NaN,
                NaN,
                NaN,
                NaN,
                0.9682539682539681,
                0.9909090909090909,
                0.9404704670329671,
                0.9822770947193737,
                0.9876506463694842,
                0.9686572189655217
              ],
              "auroc_per_k": [
                NaN,
                NaN,
                NaN,
                NaN,
                0.9969278033794163,
                0.9988888888888889,
                0.9858630952380952,
                0.9941333333333333,
                0.9936680235187698,
                0.9335142469470828
              ],
              "horizon_labels": [
                1,
                2,
                3,
                5,
                10,
                15,
                20,
                30,
                50,
                100
              ],
              "prevalence_per_k": [
                0.0,
                0.0,
                0.0,
                0.0,
                0.07,
                0.1,
                0.16,
                0.25,
                0.33,
                0.67
              ]
            },
            "monotonicity": {
              "violation_rate": 0.0,
              "mean_violation": 0.0,
              "max_violation": 0.0,
              "n_pairs": 900
            },
            "legacy": {
              "rmse_cross": 12.357184410095215,
              "rmse_expected": 14.525973320007324,
              "rmse_uncapped": 23.46956443786621,
              "nasa_score": 229.39059448242188,
              "horizon_cap": 100.0
            },
            "train": {
              "best_val": 0.24902009805043537,
              "final_epoch": 31
            },
            "pos_weight": 7.284600389863548,
            "n_train_items": 425,
            "surface_file": "/home/sagemaker-user/IndustrialJEPA/fam-jepa/experiments/v21/surfaces/fd001_e2e_b100_seed42.npz",
            "runtime_s": 7.748826742172241
          },
          {
            "subset": "FD001",
            "mode": "e2e",
            "budget": 1.0,
            "seed": 123,
            "primary": {
              "auprc": 0.956307095766261,
              "auroc": 0.990991160287441,
              "f1_best": 0.8938906752411575,
              "precision_best": 0.9084967320261438,
              "recall_best": 0.879746835443038,
              "threshold_best": 0.9613175392150879,
              "prevalence": 0.158,
              "n_cells": 1000,
              "n_positive": 158
            },
            "per_horizon": {
              "auprc_per_k": [
                NaN,
                NaN,
                NaN,
                NaN,
                0.9999999999999998,
                0.9451515151515152,
                0.892710375772636,
                0.990213058117406,
                0.9848172436882113,
                0.9635368314453092
              ],
              "auroc_per_k": [
                NaN,
                NaN,
                NaN,
                NaN,
                1.0,
                0.9933333333333333,
                0.9799107142857142,
                0.9968,
                0.9914066033469019,
                0.9176843057440073
              ],
              "horizon_labels": [
                1,
                2,
                3,
                5,
                10,
                15,
                20,
                30,
                50,
                100
              ],
              "prevalence_per_k": [
                0.0,
                0.0,
                0.0,
                0.0,
                0.07,
                0.1,
                0.16,
                0.25,
                0.33,
                0.67
              ]
            },
            "monotonicity": {
              "violation_rate": 0.0,
              "mean_violation": 0.0,
              "max_violation": 0.0,
              "n_pairs": 900
            },
            "legacy": {
              "rmse_cross": 10.96722412109375,
              "rmse_expected": 16.46463394165039,
              "rmse_uncapped": 25.818302154541016,
              "nasa_score": 291.3250427246094,
              "horizon_cap": 100.0
            },
            "train": {
              "best_val": 0.2435067507425944,
              "final_epoch": 13
            },
            "pos_weight": 8.340659340659341,
            "n_train_items": 425,
            "surface_file": "/home/sagemaker-user/IndustrialJEPA/fam-jepa/experiments/v21/surfaces/fd001_e2e_b100_seed123.npz",
            "runtime_s": 3.3467023372650146
          },
          {
            "subset": "FD001",
            "mode": "e2e",
            "budget": 1.0,
            "seed": 456,
            "primary": {
              "auprc": 0.9598019053542616,
              "auroc": 0.9904311614901231,
              "f1_best": 0.8835616438356164,
              "precision_best": 0.9626865671641791,
              "recall_best": 0.8164556962025317,
              "threshold_best": 0.9830511212348938,
              "prevalence": 0.158,
              "n_cells": 1000,
              "n_positive": 158
            },
            "per_horizon": {
              "auprc_per_k": [
                NaN,
                NaN,
                NaN,
                NaN,
                0.9367346938775509,
                0.9622222222222222,
                0.9543351715686275,
                0.9748521167987436,
                0.9999999999999999,
                0.9612469186641426
              ],
              "auroc_per_k": [
                NaN,
                NaN,
                NaN,
                NaN,
                0.9938556067588326,
                0.9955555555555555,
                0.9903273809523809,
                0.9914666666666667,
                1.0,
                0.9077340569877883
              ],
              "horizon_labels": [
                1,
                2,
                3,
                5,
                10,
                15,
                20,
                30,
                50,
                100
              ],
              "prevalence_per_k": [
                0.0,
                0.0,
                0.0,
                0.0,
                0.07,
                0.1,
                0.16,
                0.25,
                0.33,
                0.67
              ]
            },
            "monotonicity": {
              "violation_rate": 0.0,
              "mean_violation": 0.0,
              "max_violation": 0.0,
              "n_pairs": 900
            },
            "legacy": {
              "rmse_cross": 12.024142265319824,
              "rmse_expected": 12.948311805725098,
              "rmse_uncapped": 22.3632755279541,
              "nasa_score": 178.70013427734375,
              "horizon_cap": 100.0
            },
            "train": {
              "best_val": 0.24476907698313397,
              "final_epoch": 17
            },
            "pos_weight": 7.1106870229007635,
            "n_train_items": 425,
            "surface_file": "/home/sagemaker-user/IndustrialJEPA/fam-jepa/experiments/v21/surfaces/fd001_e2e_b100_seed456.npz",
            "runtime_s": 4.333972454071045
          }
        ],
        "auprc_mean": 0.9615357375345243,
        "auprc_std": 0.006277774775111115,
        "auprc_ci95_lo": 0.945940880469989,
        "auprc_ci95_hi": 0.9771305945990595,
        "auroc_mean": 0.9917403309379917,
        "auroc_std": 0.0018044313879503658,
        "auroc_ci95_lo": 0.9872578748789738,
        "auroc_ci95_hi": 0.9962227869970097,
        "f1_best_mean": 0.8953296348142091,
        "f1_best_std": 0.012549497185120566,
        "f1_best_ci95_lo": 0.8641549555935328,
        "f1_best_ci95_hi": 0.9265043140348854,
        "precision_best_mean": 0.9158846291418724,
        "precision_best_std": 0.043580207933314505,
        "precision_best_ci95_lo": 0.8076253911301465,
        "precision_best_ci95_hi": 1.0241438671535983,
        "recall_best_mean": 0.8797468354430379,
        "recall_best_std": 0.06329113924050633,
        "recall_best_ci95_lo": 0.7225229296380034,
        "recall_best_ci95_hi": 1.0369707412480724,
        "rmse_expected_mean": 14.646306355794271,
        "rmse_expected_std": 1.7612468227156097,
        "rmse_expected_ci95_lo": 10.271126703840196,
        "rmse_expected_ci95_hi": 19.021486007748347,
        "rmse_cross_mean": 11.78285026550293,
        "rmse_cross_std": 0.7257160416664262,
        "rmse_cross_ci95_lo": 9.980071678399527,
        "rmse_cross_ci95_hi": 13.585628852606332,
        "nasa_mean": 233.13859049479166,
        "nasa_std": 56.40592261695837,
        "nasa_ci95_lo": 93.01851095767091,
        "nasa_ci95_hi": 373.2586700319124,
        "mono_violation_mean": 0.0,
        "mono_violation_std": 0.0,
        "mono_violation_ci95_lo": 0.0,
        "mono_violation_ci95_hi": 0.0
      },
      "e2e@0.05": {
        "n_seeds": 3,
        "per_seed": [
          {
            "subset": "FD001",
            "mode": "e2e",
            "budget": 0.05,
            "seed": 42,
            "primary": {
              "auprc": 0.8540125831688631,
              "auroc": 0.9678282570131393,
              "f1_best": 0.8013029315960912,
              "precision_best": 0.825503355704698,
              "recall_best": 0.7784810126582279,
              "threshold_best": 0.8750897645950317,
              "prevalence": 0.158,
              "n_cells": 1000,
              "n_positive": 158
            },
            "per_horizon": {
              "auprc_per_k": [
                NaN,
                NaN,
                NaN,
                NaN,
                0.8631519274376416,
                0.8980006105006104,
                0.8793812628941939,
                0.9261538128312978,
                0.900021709668176,
                0.9163650629422467
              ],
              "auroc_per_k": [
                NaN,
                NaN,
                NaN,
                NaN,
                0.989247311827957,
                0.9866666666666667,
                0.9672619047619048,
                0.9733333333333334,
                0.9534147444595206,
                0.8534599728629579
              ],
              "horizon_labels": [
                1,
                2,
                3,
                5,
                10,
                15,
                20,
                30,
                50,
                100
              ],
              "prevalence_per_k": [
                0.0,
                0.0,
                0.0,
                0.0,
                0.07,
                0.1,
                0.16,
                0.25,
                0.33,
                0.67
              ]
            },
            "monotonicity": {
              "violation_rate": 0.0,
              "mean_violation": 0.0,
              "max_violation": 0.0,
              "n_pairs": 900
            },
            "legacy": {
              "rmse_cross": 18.706684112548828,
              "rmse_expected": 19.95118522644043,
              "rmse_uncapped": 27.176464080810547,
              "nasa_score": 679.3269653320312,
              "horizon_cap": 100.0
            },
            "train": {
              "best_val": 0.5256495513916015,
              "final_epoch": 31
            },
            "pos_weight": 6.142857142857143,
            "n_train_items": 20,
            "surface_file": "/home/sagemaker-user/IndustrialJEPA/fam-jepa/experiments/v21/surfaces/fd001_e2e_b5_seed42.npz",
            "runtime_s": 1.548259973526001
          },
          {
            "subset": "FD001",
            "mode": "e2e",
            "budget": 0.05,
            "seed": 123,
            "primary": {
              "auprc": 0.49018991577095544,
              "auroc": 0.874789530653357,
              "f1_best": 0.5553470919324578,
              "precision_best": 0.39466666666666667,
              "recall_best": 0.9367088607594937,
              "threshold_best": 0.48789483308792114,
              "prevalence": 0.158,
              "n_cells": 1000,
              "n_positive": 158
            },
            "per_horizon": {
              "auprc_per_k": [
                NaN,
                NaN,
                NaN,
                NaN,
                0.8214285714285714,
                0.8175396825396825,
                0.8537459068709069,
                0.953116555044742,
                0.9738024789468578,
                0.9464378964807066
              ],
              "auroc_per_k": [
                NaN,
                NaN,
                NaN,
                NaN,
                0.9861751152073733,
                0.9822222222222222,
                0.9791666666666667,
                0.9866666666666667,
                0.9855269109000452,
                0.8796924468566261
              ],
              "horizon_labels": [
                1,
                2,
                3,
                5,
                10,
                15,
                20,
                30,
                50,
                100
              ],
              "prevalence_per_k": [
                0.0,
                0.0,
                0.0,
                0.0,
                0.07,
                0.1,
                0.16,
                0.25,
                0.33,
                0.67
              ]
            },
            "monotonicity": {
              "violation_rate": 0.0,
              "mean_violation": 0.0,
              "max_violation": 0.0,
              "n_pairs": 900
            },
            "legacy": {
              "rmse_cross": 21.30281639099121,
              "rmse_expected": 21.093414306640625,
              "rmse_uncapped": 30.86878776550293,
              "nasa_score": 603.2063598632812,
              "horizon_cap": 100.0
            },
            "train": {
              "best_val": 1.0302180786132813,
              "final_epoch": 18
            },
            "pos_weight": 11.5,
            "n_train_items": 20,
            "surface_file": "/home/sagemaker-user/IndustrialJEPA/fam-jepa/experiments/v21/surfaces/fd001_e2e_b5_seed123.npz",
            "runtime_s": 0.988300085067749
          },
          {
            "subset": "FD001",
            "mode": "e2e",
            "budget": 0.05,
            "seed": 456,
            "primary": {
              "auprc": 0.832708547106616,
              "auroc": 0.9536103009711657,
              "f1_best": 0.728643216080402,
              "precision_best": 0.6041666666666666,
              "recall_best": 0.9177215189873418,
              "threshold_best": 0.38065701723098755,
              "prevalence": 0.158,
              "n_cells": 1000,
              "n_positive": 158
            },
            "per_horizon": {
              "auprc_per_k": [
                NaN,
                NaN,
                NaN,
                NaN,
                0.5914813156192467,
                0.7084873949579831,
                0.7936873957468923,
                0.867477187413188,
                0.9480839469101733,
                0.9473371339497658
              ],
              "auroc_per_k": [
                NaN,
                NaN,
                NaN,
                NaN,
                0.935483870967742,
                0.9477777777777778,
                0.9441964285714285,
                0.9541333333333333,
                0.979194934418815,
                0.89280868385346
              ],
              "horizon_labels": [
                1,
                2,
                3,
                5,
                10,
                15,
                20,
                30,
                50,
                100
              ],
              "prevalence_per_k": [
                0.0,
                0.0,
                0.0,
                0.0,
                0.07,
                0.1,
                0.16,
                0.25,
                0.33,
                0.67
              ]
            },
            "monotonicity": {
              "violation_rate": 0.0,
              "mean_violation": 0.0,
              "max_violation": 0.0,
              "n_pairs": 900
            },
            "legacy": {
              "rmse_cross": 16.962310791015625,
              "rmse_expected": 18.06586456298828,
              "rmse_uncapped": 27.138206481933594,
              "nasa_score": 428.3391418457031,
              "horizon_cap": 100.0
            },
            "train": {
              "best_val": 0.6939874013264974,
              "final_epoch": 19
            },
            "pos_weight": 6.142857142857143,
            "n_train_items": 20,
            "surface_file": "/home/sagemaker-user/IndustrialJEPA/fam-jepa/experiments/v21/surfaces/fd001_e2e_b5_seed456.npz",
            "runtime_s": 1.0722453594207764
          }
        ],
        "auprc_mean": 0.7256370153488115,
        "auprc_std": 0.20418121366289807,
        "auprc_ci95_lo": 0.21842276246414027,
        "auprc_ci95_hi": 1.2328512682334827,
        "auroc_mean": 0.9320760295458873,
        "auroc_std": 0.05011830788270676,
        "auroc_ci95_lo": 0.8075752508868844,
        "auroc_ci95_hi": 1.05657680820489,
        "f1_best_mean": 0.695097746536317,
        "f1_best_std": 0.12636274237828407,
        "f1_best_ci95_lo": 0.3811952928381199,
        "f1_best_ci95_hi": 1.009000200234514,
        "precision_best_mean": 0.6081122296793438,
        "precision_best_std": 0.2154454426436739,
        "precision_best_ci95_lo": 0.07291608079008305,
        "precision_best_ci95_hi": 1.1433083785686045,
        "recall_best_mean": 0.8776371308016877,
        "recall_best_std": 0.08639491657992938,
        "recall_best_ci95_lo": 0.6630202604246209,
        "recall_best_ci95_hi": 1.0922540011787545,
        "rmse_expected_mean": 19.703488032023113,
        "rmse_expected_std": 1.5288982267188358,
        "rmse_expected_ci95_lo": 15.905494289649713,
        "rmse_expected_ci95_hi": 23.501481774396513,
        "rmse_cross_mean": 18.990603764851887,
        "rmse_cross_std": 2.1841371276954598,
        "rmse_cross_ci95_lo": 13.564906358376785,
        "rmse_cross_ci95_hi": 24.41630117132699,
        "nasa_mean": 570.2908223470052,
        "nasa_std": 128.69070029372784,
        "nasa_ci95_lo": 250.6054005997583,
        "nasa_ci95_hi": 889.9762440942523,
        "mono_violation_mean": 0.0,
        "mono_violation_std": 0.0,
        "mono_violation_ci95_lo": 0.0,
        "mono_violation_ci95_hi": 0.0
      },
      "scratch@1.0": {
        "n_seeds": 3,
        "per_seed": [
          {
            "subset": "FD001",
            "mode": "scratch",
            "budget": 1.0,
            "seed": 42,
            "primary": {
              "auprc": 0.9482378106733057,
              "auroc": 0.9888225743407799,
              "f1_best": 0.8703703703703705,
              "precision_best": 0.8493975903614458,
              "recall_best": 0.8924050632911392,
              "threshold_best": 0.9354735016822815,
              "prevalence": 0.158,
              "n_cells": 1000,
              "n_positive": 158
            },
            "per_horizon": {
              "auprc_per_k": [
                NaN,
                NaN,
                NaN,
                NaN,
                0.8909090909090909,
                0.932651515151515,
                0.8797619449793364,
                0.9673222057547406,
                0.9781752386769236,
                0.9578159842299384
              ],
              "auroc_per_k": [
                NaN,
                NaN,
                NaN,
                NaN,
                0.9877112135176652,
                0.9922222222222222,
                0.96875,
                0.9904000000000001,
                0.9882406151062868,
                0.9086386250565355
              ],
              "horizon_labels": [
                1,
                2,
                3,
                5,
                10,
                15,
                20,
                30,
                50,
                100
              ],
              "prevalence_per_k": [
                0.0,
                0.0,
                0.0,
                0.0,
                0.07,
                0.1,
                0.16,
                0.25,
                0.33,
                0.67
              ]
            },
            "monotonicity": {
              "violation_rate": 0.0,
              "mean_violation": 0.0,
              "max_violation": 0.0,
              "n_pairs": 900
            },
            "legacy": {
              "rmse_cross": 16.86119842529297,
              "rmse_expected": 20.874473571777344,
              "rmse_uncapped": 28.994857788085938,
              "nasa_score": 583.0478515625,
              "horizon_cap": 100.0
            },
            "train": {
              "best_val": 0.2965439542134603,
              "final_epoch": 32
            },
            "pos_weight": 7.284600389863548,
            "n_train_items": 425,
            "surface_file": "/home/sagemaker-user/IndustrialJEPA/fam-jepa/experiments/v21/surfaces/fd001_scratch_b100_seed42.npz",
            "runtime_s": 7.883206844329834
          },
          {
            "subset": "FD001",
            "mode": "scratch",
            "budget": 1.0,
            "seed": 123,
            "primary": {
              "auprc": 0.9378538587205972,
              "auroc": 0.9861917075077422,
              "f1_best": 0.8504398826979471,
              "precision_best": 0.7923497267759563,
              "recall_best": 0.9177215189873418,
              "threshold_best": 0.8536088466644287,
              "prevalence": 0.158,
              "n_cells": 1000,
              "n_positive": 158
            },
            "per_horizon": {
              "auprc_per_k": [
                NaN,
                NaN,
                NaN,
                NaN,
                0.9682539682539681,
                0.8988235294117647,
                0.8725643520444721,
                0.9868313731357211,
                0.9794736749173314,
                0.9529738822975613
              ],
              "auroc_per_k": [
                NaN,
                NaN,
                NaN,
                NaN,
                0.9969278033794163,
                0.9833333333333334,
                0.9747023809523809,
                0.9957333333333334,
                0.9886928991406603,
                0.8977838082315694
              ],
              "horizon_labels": [
                1,
                2,
                3,
                5,
                10,
                15,
                20,
                30,
                50,
                100
              ],
              "prevalence_per_k": [
                0.0,
                0.0,
                0.0,
                0.0,
                0.07,
                0.1,
                0.16,
                0.25,
                0.33,
                0.67
              ]
            },
            "monotonicity": {
              "violation_rate": 0.0,
              "mean_violation": 0.0,
              "max_violation": 0.0,
              "n_pairs": 900
            },
            "legacy": {
              "rmse_cross": 13.484435081481934,
              "rmse_expected": 14.785416603088379,
              "rmse_uncapped": 23.842811584472656,
              "nasa_score": 237.01414489746094,
              "horizon_cap": 100.0
            },
            "train": {
              "best_val": 0.3641384493509928,
              "final_epoch": 35
            },
            "pos_weight": 8.340659340659341,
            "n_train_items": 425,
            "surface_file": "/home/sagemaker-user/IndustrialJEPA/fam-jepa/experiments/v21/surfaces/fd001_scratch_b100_seed123.npz",
            "runtime_s": 8.484977006912231
          },
          {
            "subset": "FD001",
            "mode": "scratch",
            "budget": 1.0,
            "seed": 456,
            "primary": {
              "auprc": 0.9274227232405234,
              "auroc": 0.984718422081241,
              "f1_best": 0.8562300319488818,
              "precision_best": 0.864516129032258,
              "recall_best": 0.8481012658227848,
              "threshold_best": 0.9368153214454651,
              "prevalence": 0.158,
              "n_cells": 1000,
              "n_positive": 158
            },
            "per_horizon": {
              "auprc_per_k": [
                NaN,
                NaN,
                NaN,
                NaN,
                0.8864468864468864,
                0.8897546897546896,
                0.9029608823194349,
                0.9518130650465486,
                0.9557997620627197,
                0.944528102392126
              ],
              "auroc_per_k": [
                NaN,
                NaN,
                NaN,
                NaN,
                0.9861751152073733,
                0.9866666666666667,
                0.9747023809523809,
                0.9807999999999999,
                0.9746720940750792,
                0.8932609678878336
              ],
              "horizon_labels": [
                1,
                2,
                3,
                5,
                10,
                15,
                20,
                30,
                50,
                100
              ],
              "prevalence_per_k": [
                0.0,
                0.0,
                0.0,
                0.0,
                0.07,
                0.1,
                0.16,
                0.25,
                0.33,
                0.67
              ]
            },
            "monotonicity": {
              "violation_rate": 0.0,
              "mean_violation": 0.0,
              "max_violation": 0.0,
              "n_pairs": 900
            },
            "legacy": {
              "rmse_cross": 19.310619354248047,
              "rmse_expected": 23.294313430786133,
              "rmse_uncapped": 31.76605224609375,
              "nasa_score": 877.678955078125,
              "horizon_cap": 100.0
            },
            "train": {
              "best_val": 0.36461179224650064,
              "final_epoch": 24
            },
            "pos_weight": 7.1106870229007635,
            "n_train_items": 425,
            "surface_file": "/home/sagemaker-user/IndustrialJEPA/fam-jepa/experiments/v21/surfaces/fd001_scratch_b100_seed456.npz",
            "runtime_s": 6.04787802696228
          }
        ],
        "auprc_mean": 0.9378381308781422,
        "auprc_std": 0.010407552629334321,
        "auprc_ci95_lo": 0.9119843369049069,
        "auprc_ci95_hi": 0.9636919248513774,
        "auroc_mean": 0.9865775679765877,
        "auroc_std": 0.0020791062186508768,
        "auroc_ci95_lo": 0.9814127818121664,
        "auroc_ci95_hi": 0.991742354141009,
        "f1_best_mean": 0.8590134283390665,
        "f1_best_std": 0.010252636554263707,
        "f1_best_ci95_lo": 0.8335444672300657,
        "f1_best_ci95_hi": 0.8844823894480672,
        "precision_best_mean": 0.83542114872322,
        "precision_best_std": 0.03805920511919078,
        "precision_best_ci95_lo": 0.7408768420085686,
        "precision_best_ci95_hi": 0.9299654554378715,
        "recall_best_mean": 0.8860759493670886,
        "recall_best_std": 0.03523901495462041,
        "recall_best_ci95_lo": 0.798537383394467,
        "recall_best_ci95_hi": 0.9736145153397101,
        "rmse_expected_mean": 19.651401201883953,
        "rmse_expected_std": 4.384319881418178,
        "rmse_expected_ci95_lo": 8.76014684421129,
        "rmse_expected_ci95_hi": 30.542655559556614,
        "rmse_cross_mean": 16.55208428700765,
        "rmse_cross_std": 2.925366551036418,
        "rmse_cross_ci95_lo": 9.28507091697514,
        "rmse_cross_ci95_hi": 23.819097657040157,
        "nasa_mean": 565.9136505126953,
        "nasa_std": 320.6759039671798,
        "nasa_ci95_lo": -230.68945577193153,
        "nasa_ci95_hi": 1362.5167567973222,
        "mono_violation_mean": 0.0,
        "mono_violation_std": 0.0,
        "mono_violation_ci95_lo": 0.0,
        "mono_violation_ci95_hi": 0.0
      },
      "scratch@0.05": {
        "n_seeds": 3,
        "per_seed": [
          {
            "subset": "FD001",
            "mode": "scratch",
            "budget": 0.05,
            "seed": 42,
            "primary": {
              "auprc": 0.7380808868767852,
              "auroc": 0.938400132295018,
              "f1_best": 0.6712802768166091,
              "precision_best": 0.7404580152671756,
              "recall_best": 0.6139240506329114,
              "threshold_best": 0.9002115726470947,
              "prevalence": 0.158,
              "n_cells": 1000,
              "n_positive": 158
            },
            "per_horizon": {
              "auprc_per_k": [
                NaN,
                NaN,
                NaN,
                NaN,
                0.2990580847723705,
                0.3753295607900871,
                0.4974786042438271,
                0.5561420490843222,
                0.6872953147126082,
                0.8980187165807556
              ],
              "auroc_per_k": [
                NaN,
                NaN,
                NaN,
                NaN,
                0.9062980030721967,
                0.8888888888888888,
                0.890625,
                0.8698666666666667,
                0.8815015829941204,
                0.8661239258254183
              ],
              "horizon_labels": [
                1,
                2,
                3,
                5,
                10,
                15,
                20,
                30,
                50,
                100
              ],
              "prevalence_per_k": [
                0.0,
                0.0,
                0.0,
                0.0,
                0.07,
                0.1,
                0.16,
                0.25,
                0.33,
                0.67
              ]
            },
            "monotonicity": {
              "violation_rate": 0.0,
              "mean_violation": 0.0,
              "max_violation": 0.0,
              "n_pairs": 900
            },
            "legacy": {
              "rmse_cross": 30.75743865966797,
              "rmse_expected": 35.174964904785156,
              "rmse_uncapped": 43.8607063293457,
              "nasa_score": 3692.84521484375,
              "horizon_cap": 100.0
            },
            "train": {
              "best_val": 0.666687297821045,
              "final_epoch": 19
            },
            "pos_weight": 6.142857142857143,
            "n_train_items": 20,
            "surface_file": "/home/sagemaker-user/IndustrialJEPA/fam-jepa/experiments/v21/surfaces/fd001_scratch_b5_seed42.npz",
            "runtime_s": 0.963294506072998
          },
          {
            "subset": "FD001",
            "mode": "scratch",
            "budget": 0.05,
            "seed": 123,
            "primary": {
              "auprc": 0.4538563357344485,
              "auroc": 0.857192789921525,
              "f1_best": 0.5595567867036011,
              "precision_best": 0.4975369458128079,
              "recall_best": 0.6392405063291139,
              "threshold_best": 0.7886778712272644,
              "prevalence": 0.158,
              "n_cells": 1000,
              "n_positive": 158
            },
            "per_horizon": {
              "auprc_per_k": [
                NaN,
                NaN,
                NaN,
                NaN,
                0.26287200685696926,
                0.2957598541809068,
                0.40724249641121724,
                0.5025470870386652,
                0.628128998287232,
                0.8873129948632081
              ],
              "auroc_per_k": [
                NaN,
                NaN,
                NaN,
                NaN,
                0.8847926267281105,
                0.8111111111111111,
                0.8110119047619048,
                0.7952,
                0.8154681139755767,
                0.8113975576662144
              ],
              "horizon_labels": [
                1,
                2,
                3,
                5,
                10,
                15,
                20,
                30,
                50,
                100
              ],
              "prevalence_per_k": [
                0.0,
                0.0,
                0.0,
                0.0,
                0.07,
                0.1,
                0.16,
                0.25,
                0.33,
                0.67
              ]
            },
            "monotonicity": {
              "violation_rate": 0.0,
              "mean_violation": 0.0,
              "max_violation": 0.0,
              "n_pairs": 900
            },
            "legacy": {
              "rmse_cross": 68.61457824707031,
              "rmse_expected": 49.715538024902344,
              "rmse_uncapped": 59.28324890136719,
              "nasa_score": 10077.21484375,
              "horizon_cap": 100.0
            },
            "train": {
              "best_val": 1.225137741088867,
              "final_epoch": 15
            },
            "pos_weight": 11.5,
            "n_train_items": 20,
            "surface_file": "/home/sagemaker-user/IndustrialJEPA/fam-jepa/experiments/v21/surfaces/fd001_scratch_b5_seed123.npz",
            "runtime_s": 0.777014970779419
          },
          {
            "subset": "FD001",
            "mode": "scratch",
            "budget": 0.05,
            "seed": 456,
            "primary": {
              "auprc": 0.7453363731423869,
              "auroc": 0.9278315643885865,
              "f1_best": 0.664864864864865,
              "precision_best": 0.5801886792452831,
              "recall_best": 0.7784810126582279,
              "threshold_best": 0.7224957942962646,
              "prevalence": 0.158,
              "n_cells": 1000,
              "n_positive": 158
            },
            "per_horizon": {
              "auprc_per_k": [
                NaN,
                NaN,
                NaN,
                NaN,
                0.4409383849233473,
                0.44439621781727046,
                0.6400770763822234,
                0.6775309426141065,
                0.7293970547375833,
                0.9086248300515516
              ],
              "auroc_per_k": [
                NaN,
                NaN,
                NaN,
                NaN,
                0.9201228878648233,
                0.8855555555555555,
                0.8690476190476191,
                0.8314666666666667,
                0.840343735866124,
                0.8426051560379918
              ],
              "horizon_labels": [
                1,
                2,
                3,
                5,
                10,
                15,
                20,
                30,
                50,
                100
              ],
              "prevalence_per_k": [
                0.0,
                0.0,
                0.0,
                0.0,
                0.07,
                0.1,
                0.16,
                0.25,
                0.33,
                0.67
              ]
            },
            "monotonicity": {
              "violation_rate": 0.0,
              "mean_violation": 0.0,
              "max_violation": 0.0,
              "n_pairs": 900
            },
            "legacy": {
              "rmse_cross": 38.70413589477539,
              "rmse_expected": 39.08000183105469,
              "rmse_uncapped": 47.370384216308594,
              "nasa_score": 6592.06591796875,
              "horizon_cap": 100.0
            },
            "train": {
              "best_val": 0.7040469614664714,
              "final_epoch": 18
            },
            "pos_weight": 6.142857142857143,
            "n_train_items": 20,
            "surface_file": "/home/sagemaker-user/IndustrialJEPA/fam-jepa/experiments/v21/surfaces/fd001_scratch_b5_seed456.npz",
            "runtime_s": 0.9134843349456787
          }
        ],
        "auprc_mean": 0.6457578652512068,
        "auprc_std": 0.16623118929187458,
        "auprc_ci95_lo": 0.23281669906727087,
        "auprc_ci95_hi": 1.0586990314351428,
        "auroc_mean": 0.9078081622017099,
        "auroc_std": 0.04415156384766555,
        "auroc_ci95_lo": 0.7981295974163306,
        "auroc_ci95_hi": 1.0174867269870893,
        "f1_best_mean": 0.631900642795025,
        "f1_best_std": 0.06273367925811572,
        "f1_best_ci95_lo": 0.47606154435502146,
        "f1_best_ci95_hi": 0.7877397412350285,
        "precision_best_mean": 0.6060612134417555,
        "precision_best_std": 0.12350992881353369,
        "precision_best_ci95_lo": 0.29924554150425986,
        "precision_best_ci95_hi": 0.912876885379251,
        "recall_best_mean": 0.6772151898734178,
        "recall_best_std": 0.08860759493670887,
        "recall_best_ci95_lo": 0.45710172174636937,
        "recall_best_ci95_hi": 0.8973286580004662,
        "rmse_expected_mean": 41.32350158691406,
        "rmse_expected_std": 7.525425903646545,
        "rmse_expected_ci95_lo": 22.629307302914537,
        "rmse_expected_ci95_hi": 60.017695870913585,
        "rmse_cross_mean": 46.025384267171226,
        "rmse_cross_std": 19.962245934081363,
        "rmse_cross_ci95_lo": -3.5635836683004527,
        "rmse_cross_ci95_hi": 95.6143522026429,
        "nasa_mean": 6787.375325520833,
        "nasa_std": 3196.662824436429,
        "nasa_ci95_lo": -1153.5753483136186,
        "nasa_ci95_hi": 14728.325999355286,
        "mono_violation_mean": 0.0,
        "mono_violation_std": 0.0,
        "mono_violation_ci95_lo": 0.0,
        "mono_violation_ci95_hi": 0.0
      }
    },
    "FD002": {
      "pred_ft@1.0": {
        "n_seeds": 0,
        "per_seed": [],
        "auprc_mean": NaN,
        "auprc_std": NaN,
        "auroc_mean": NaN,
        "auroc_std": NaN,
        "f1_best_mean": NaN,
        "f1_best_std": NaN,
        "precision_best_mean": NaN,
        "precision_best_std": NaN,
        "recall_best_mean": NaN,
        "recall_best_std": NaN,
        "rmse_expected_mean": NaN,
        "rmse_expected_std": NaN,
        "rmse_cross_mean": NaN,
        "rmse_cross_std": NaN,
        "nasa_mean": NaN,
        "nasa_std": NaN,
        "mono_violation_mean": NaN,
        "mono_violation_std": NaN
      },
      "pred_ft@0.05": {
        "n_seeds": 0,
        "per_seed": [],
        "auprc_mean": NaN,
        "auprc_std": NaN,
        "auroc_mean": NaN,
        "auroc_std": NaN,
        "f1_best_mean": NaN,
        "f1_best_std": NaN,
        "precision_best_mean": NaN,
        "precision_best_std": NaN,
        "recall_best_mean": NaN,
        "recall_best_std": NaN,
        "rmse_expected_mean": NaN,
        "rmse_expected_std": NaN,
        "rmse_cross_mean": NaN,
        "rmse_cross_std": NaN,
        "nasa_mean": NaN,
        "nasa_std": NaN,
        "mono_violation_mean": NaN,
        "mono_violation_std": NaN
      }
    },
    "FD003": {
      "pred_ft@1.0": {
        "n_seeds": 0,
        "per_seed": [],
        "auprc_mean": NaN,
        "auprc_std": NaN,
        "auroc_mean": NaN,
        "auroc_std": NaN,
        "f1_best_mean": NaN,
        "f1_best_std": NaN,
        "precision_best_mean": NaN,
        "precision_best_std": NaN,
        "recall_best_mean": NaN,
        "recall_best_std": NaN,
        "rmse_expected_mean": NaN,
        "rmse_expected_std": NaN,
        "rmse_cross_mean": NaN,
        "rmse_cross_std": NaN,
        "nasa_mean": NaN,
        "nasa_std": NaN,
        "mono_violation_mean": NaN,
        "mono_violation_std": NaN
      },
      "pred_ft@0.05": {
        "n_seeds": 0,
        "per_seed": [],
        "auprc_mean": NaN,
        "auprc_std": NaN,
        "auroc_mean": NaN,
        "auroc_std": NaN,
        "f1_best_mean": NaN,
        "f1_best_std": NaN,
        "precision_best_mean": NaN,
        "precision_best_std": NaN,
        "recall_best_mean": NaN,
        "recall_best_std": NaN,
        "rmse_expected_mean": NaN,
        "rmse_expected_std": NaN,
        "rmse_cross_mean": NaN,
        "rmse_cross_std": NaN,
        "nasa_mean": NaN,
        "nasa_std": NaN,
        "mono_violation_mean": NaN,
        "mono_violation_std": NaN
      }
    }
  },
  "seeds": [
    42,
    123,
    456
  ],
  "runtime_min": 1.3120544036229451
}